{"utterance_id": "1eoSQxxBXtk.en_240.24_251.52", "speaker_id": "4E36078E", "session_id": "1eoSQxxBXtk", "audio_path": "audio-utterance/1eoSQxxBXtk/1eoSQxxBXtk.en_240.24_251.52.wav", "duration_in_seconds": "11.28", "domain": "clothing", "topic": "clothing", "transcription": "so now that you understand how the color separation process works and how the screens are made from it it's time for us to dive into how the colors that are applied to your t-shirts are actually mixed and made in production so", "language": "English", "accent": "en_us", "age_group": "adult", "gender": "male", "noise_background": "clean", "sampling_rate": "16000", "samplint_bit": "16"}