{
  "speaker_id": "4E36078G",
  "utterce_ids_list": ["1eoSQxxBXtk.en_214.96_226.0", "1eoSQxxBXtk.en_255.12_260.08", "1eoSQxxBXtk.en_262.64_271.52", "1eoSQxxBXtk.en_275.12_278.08", "1eoSQxxBXtk.en_279.36_282.48", "1eoSQxxBXtk.en_288.32_288.72", "1eoSQxxBXtk.en_291.68_297.28", "1eoSQxxBXtk.en_302.8_329.84", "1eoSQxxBXtk.en_335.52_339.36", "1eoSQxxBXtk.en_343.36_344.72", "1eoSQxxBXtk.en_346.48_369.92", "1eoSQxxBXtk.en_372.08_372.24", "1eoSQxxBXtk.en_375.6_375.68", "1eoSQxxBXtk.en_378.0_378.4", "1eoSQxxBXtk.en_384.56_408.48", "1eoSQxxBXtk.en_412.64_414.48", "1eoSQxxBXtk.en_418.88_427.92", "1eoSQxxBXtk.en_436.56_454.24", "1eoSQxxBXtk.en_464.24_466.08", "1eoSQxxBXtk.en_469.28_469.6", "1eoSQxxBXtk.en_476.96_477.2"],
  "context_ids_list": ["1eoSQxxBXtk"],
  "duration_in_minutes": 2.47,
  "language": "English",
  "accent": "en_us",
  "gender": "female"
}
